llm_docs.py
llm_docs-0.2.1.dist-info/licenses/LICENSE
llm_docs-0.2.1.dist-info/METADATA
llm_docs-0.2.1.dist-info/WHEEL
llm_docs-0.2.1.dist-info/entry_points.txt
llm_docs-0.2.1.dist-info/top_level.txt
llm_docs-0.2.1.dist-info/RECORD
