Metadata-Version: 2.4
Name: llm-docs
Version: 0.2.1
Summary: Ask questions of LLM documentation using LLM
Author: Simon Willison
License: Apache-2.0
Project-URL: Homepage, https://github.com/simonw/llm-docs
Project-URL: Changelog, https://github.com/simonw/llm-docs/releases
Project-URL: Issues, https://github.com/simonw/llm-docs/issues
Project-URL: CI, https://github.com/simonw/llm-docs/actions
Classifier: License :: OSI Approved :: Apache Software License
Requires-Python: >=3.9
License-File: LICENSE
Requires-Dist: llm>=0.24
Provides-Extra: test
Requires-Dist: pytest; extra == "test"
Dynamic: license-file
